pytest_kind/__init__.py
pytest_kind/cluster.py
pytest_kind/plugin.py
ioben_pytest_kind-21.0.1.dist-info/entry_points.txt
ioben_pytest_kind-21.0.1.dist-info/LICENSE
ioben_pytest_kind-21.0.1.dist-info/WHEEL
ioben_pytest_kind-21.0.1.dist-info/METADATA
ioben_pytest_kind-21.0.1.dist-info/RECORD
