Metadata-Version: 2.1
Name: ioben-pytest-kind
Version: 21.0.1
Summary: Kubernetes test support with KIND for pytest
Home-page: https://codeberg.org/hjacobs/pytest-kind
License: GPL-3.0+
Author: Henning Jacobs
Author-email: henning@jacobs1.de
Requires-Python: >=3.7,<4.0
Classifier: Framework :: Pytest
Classifier: License :: OSI Approved :: GNU General Public License v3 or later (GPLv3+)
Classifier: Programming Language :: Python :: 3
Classifier: Programming Language :: Python :: 3.7
Classifier: Programming Language :: Python :: 3.8
Classifier: Programming Language :: Python :: 3.9
Requires-Dist: pykube-ng (>=0.30.0)
Project-URL: Repository, https://codeberg.org/hjacobs/pytest-kind
